README.txt
setup.py
sqlo_kernel/__init__.py
sqlo_kernel/kernel.py
sqlo_kernel/sqlok_install
sqlo_kernel.egg-info/PKG-INFO
sqlo_kernel.egg-info/SOURCES.txt
sqlo_kernel.egg-info/dependency_links.txt
sqlo_kernel.egg-info/requires.txt
sqlo_kernel.egg-info/top_level.txt