Metadata-Version: 2.1
Name: sqlo-kernel
Version: 0.1.3
Summary: Oracle Kernel for Jupyter Notebook
Home-page: https://github.com/mtatton/sqlok
Author: Michael Tatton
License: UNKNOWN
Platform: UNKNOWN
Classifier: Development Status :: 1 - Planning
Classifier: Intended Audience :: Science/Research
Classifier: Operating System :: POSIX :: Linux
Classifier: Programming Language :: Python :: 3.7
